deeplake/__init__.py
deeplake/__init__.pyi
deeplake/_deeplake.cpython-313-x86_64-linux-gnu.so
deeplake/_tensorflow.py
deeplake/_torch.py
deeplake/core.py
deeplake/core.pyi
deeplake/py.typed
deeplake/schemas.py
deeplake/schemas.pyi
deeplake/storage.py
deeplake/storage.pyi
deeplake/tql.py
deeplake/tql.pyi
deeplake/types.py
deeplake/types.pyi
deeplake/ingestion/__init__.py
deeplake/ingestion/coco/__init__.py
deeplake/ingestion/coco/exceptions.py
deeplake/ingestion/coco/from_coco.py
deeplake/integrations/__init__.py
deeplake/integrations/constants.py
deeplake/integrations/labelbox/__init__.py
deeplake/integrations/labelbox/converters.py
deeplake/integrations/labelbox/deeplake_utils.py
deeplake/integrations/labelbox/labelbox_.py
deeplake/integrations/labelbox/labelbox_azure_utils.py
deeplake/integrations/labelbox/labelbox_converter.py
deeplake/integrations/labelbox/labelbox_debug.py
deeplake/integrations/labelbox/labelbox_metadata_utils.py
deeplake/integrations/labelbox/labelbox_utils.py
deeplake/integrations/mm/__init__.py
deeplake/integrations/mm/exceptions.py
deeplake/integrations/mm/get_indexes.py
deeplake/integrations/mm/ipc.py
deeplake/integrations/mm/mm_common.py
deeplake/integrations/mm/mm_runners.py
deeplake/integrations/mm/upcast_array.py
deeplake/integrations/mm/warnings.py
deeplake/integrations/mm/worker_init_fn.py
deeplake/integrations/mmdet/__init__.py
deeplake/integrations/mmdet/mmdet_.py
deeplake/integrations/mmdet/mmdet_dataset_.py
deeplake/integrations/mmdet/mmdet_utils_.py
deeplake/integrations/mmdet/test_.py
deeplake/integrations/mmseg/__init__.py
deeplake/integrations/mmseg/compose_transform_.py
deeplake/integrations/mmseg/mmseg_.py
deeplake/integrations/mmseg/mmseg_dataset_.py
deeplake/integrations/mmseg/test_.py
deeplake-4.4.4.dist-info/METADATA
deeplake-4.4.4.dist-info/WHEEL
deeplake-4.4.4.dist-info/top_level.txt
deeplake-4.4.4.dist-info/RECORD
