Metadata-Version: 2.4
Name: deeplake
Version: 4.4.4
Summary: Data Lake for Multi-Modal AI Search
Author: activeloop.ai
Author-email: support@activeloop.ai
Project-URL: Documentation, https://docs.deeplake.ai/
Project-URL: Source, https://github.com/activeloopai/deeplake
Requires-Dist: numpy
Requires-Dist: deepframe
Dynamic: author
Dynamic: author-email
Dynamic: description
Dynamic: description-content-type
Dynamic: project-url
Dynamic: requires-dist
Dynamic: summary
